CHANGES.txt
README.txt
setup.cfg
setup.py
repoze/__init__.py
repoze.timeago.egg-info/PKG-INFO
repoze.timeago.egg-info/SOURCES.txt
repoze.timeago.egg-info/dependency_links.txt
repoze.timeago.egg-info/namespace_packages.txt
repoze.timeago.egg-info/not-zip-safe
repoze.timeago.egg-info/top_level.txt
repoze/timeago/__init__.py
repoze/timeago/tests.py